ralogs/__init__.py
ralogs/ralogs.py
ralogs-1.4.dist-info/LICENSE
ralogs-1.4.dist-info/METADATA
ralogs-1.4.dist-info/WHEEL
ralogs-1.4.dist-info/entry_points.txt
ralogs-1.4.dist-info/top_level.txt
ralogs-1.4.dist-info/RECORD
