Metadata-Version: 2.1
Name: ralogs
Version: 1.4
Summary: UNKNOWN
Home-page: https://github.com/barell/ralogs
Author: UNKNOWN
Author-email: UNKNOWN
License: MIT
Platform: UNKNOWN
Requires-Dist: requests
Requires-Dist: aiohttp
